core_lib/__init__.py
core_lib/models.py
core_lib/utils.py
wheelio_ashwin-0.0.3.dist-info/METADATA
wheelio_ashwin-0.0.3.dist-info/WHEEL
wheelio_ashwin-0.0.3.dist-info/top_level.txt
wheelio_ashwin-0.0.3.dist-info/RECORD
